eleganplot/__init__.py
eleganplot/pyplot.py
eleganplot/theme.py
eleganplot/utils/__init__.py
eleganplot/utils/custom_methods.py
eleganplot/utils/decorators.py
eleganplot/utils/glow.py
eleganplot/utils/gradient.py
eleganplot-0.1.1.dist-info/METADATA
eleganplot-0.1.1.dist-info/WHEEL
eleganplot-0.1.1.dist-info/entry_points.txt
eleganplot-0.1.1.dist-info/licenses/LICENSE
eleganplot-0.1.1.dist-info/RECORD
