Metadata-Version: 2.4
Name: eleganplot
Version: 0.1.1
Summary: EleganPlot — надстройка над Matplotlib для элегантной, изящной визуализации.
Project-URL: Homepage, https://github.com/AlFrauch/eleganplot
Project-URL: Repository, https://github.com/AlFrauch/eleganplot
Project-URL: Documentation, https://github.com/AlFrauch/eleganplot#readme
Project-URL: Bug Tracker, https://github.com/AlFrauch/eleganplot/issues
Author: Alex Frauch
License: MIT License
License-File: LICENSE
Keywords: matplotlib,plot,styling,themes,visualization
Classifier: Intended Audience :: Developers
Classifier: Intended Audience :: Science/Research
Classifier: License :: OSI Approved :: MIT License
Classifier: Operating System :: OS Independent
Classifier: Programming Language :: Python :: 3
Classifier: Topic :: Scientific/Engineering :: Visualization
Requires-Python: >=3.9
Requires-Dist: matplotlib>=3.7
